{
  "data":{
    "name":"Mitel 5xxx Models: [5304, 5312, 5320, 5324, 5330, 5340, 5360]",
    "id":"1",
    "directory":"53xx",
    "firmware_ver":"",
    "firmware_pkg":"NULL",
    "firmware_md5sum":"",
    "description":"Variables Issues Solved (Not writing accounts + passwords in files)",
    "configuration_files":"MN_Generic.cfg,MN_$mac.cfg",
    "changelog":"",
            "provisioning_types": [
            "tftp",
            "http"
        ],
    "model_list":[
      {
        "model":"5304",
        "lines":"2",
        "id":"1",
        "template_data":[
          "template_data.json"
        ]
      },
      {
        "model":"5312",
        "lines":"2",
        "id":"2",
        "template_data":[
          "template_data.json"
        ]
      },
      {
        "model":"5320",
        "lines":"2",
        "id":"3",
        "template_data":[
          "template_data.json"
        ]
      },
      {
        "model":"5324",
        "lines":"2",
        "id":"4",
        "template_data":[
          "template_data.json"
        ]
      },
      {
        "model":"5330",
        "lines":"2",
        "id":"5",
        "template_data":[
          "template_data.json"
        ]
      },
      {
        "model":"5340",
        "lines":"2",
        "id":"6",
        "template_data":[
          "template_data.json"
        ]
      },
      {
        "model":"5360",
        "lines":"2",
        "id":"7",
        "template_data":[
          "template_data.json"
        ]
      }
    ]
  }
}